README.md
setup.py
canceladebitos/__init__.py
canceladebitos/__main__.py
canceladebitos/bancodedados.py
canceladebitos/cancelador.py
canceladebitos/config.py
canceladebitos/dadossiapa.py
canceladebitos/valida.py
canceladebitos.egg-info/PKG-INFO
canceladebitos.egg-info/SOURCES.txt
canceladebitos.egg-info/dependency_links.txt
canceladebitos.egg-info/entry_points.txt
canceladebitos.egg-info/requires.txt
canceladebitos.egg-info/top_level.txt