Metadata-Version: 1.0
Name: canceladebitos
Version: 1.1.6
Summary: Cancelamentos dos débitos renegociados em operações de parcelamento.
Home-page: UNKNOWN
Author: Rafael Alves Ribeiro
Author-email: rafael.alves.ribeiro@gmail.com
License: UNKNOWN
Platform: UNKNOWN
